pleco/__init__.py
pleco-0.0.0.dist-info/METADATA
pleco-0.0.0.dist-info/WHEEL
pleco-0.0.0.dist-info/RECORD
