Metadata-Version: 2.1
Name: pleco
Version: 0.0.0
Summary: Straightforward data validation
Author: James Hale
Author-email: james+pleco@hale.zip
Requires-Python: >=3.9,<4.0
Classifier: Programming Language :: Python :: 3
Classifier: Programming Language :: Python :: 3.9
Classifier: Programming Language :: Python :: 3.10
Classifier: Programming Language :: Python :: 3.11
Classifier: Programming Language :: Python :: 3.12
Classifier: Programming Language :: Python :: 3.13
